psa.py
pairwise_sequence_alignment-1.0.3.dist-info/LICENSE
pairwise_sequence_alignment-1.0.3.dist-info/WHEEL
pairwise_sequence_alignment-1.0.3.dist-info/METADATA
pairwise_sequence_alignment-1.0.3.dist-info/RECORD
