Metadata-Version: 2.1
Name: pairwise-sequence-alignment
Version: 1.0.3
Summary: Global and local pairwise alignments between nucleotide/protein sequences.
Keywords: sequence alignment,nucleotide,protein,pairwise alignment,needle,water,emboss
Author-email: Andrzej Zielezinski <a.zielezinski@gmail.com>
Requires-Python: >=3.8
Classifier: License :: OSI Approved :: GNU General Public License v3 or later (GPLv3+)
Classifier: Operating System :: POSIX :: Linux
Classifier: Natural Language :: English
Classifier: Intended Audience :: Developers
Classifier: Intended Audience :: Science/Research
Classifier: Topic :: Scientific/Engineering
Classifier: Topic :: Scientific/Engineering :: Bio-Informatics
Classifier: Programming Language :: Python :: 3
Classifier: Programming Language :: Python :: 3.7
Classifier: Programming Language :: Python :: 3.8
Classifier: Programming Language :: Python :: 3.9
Classifier: Programming Language :: Python :: 3.10
Classifier: Programming Language :: Python :: 3.11
Classifier: Programming Language :: Python :: 3.12
Project-URL: Documentation, https://github.com/aziele/pairwise-sequence-alignment
Project-URL: Source, https://github.com/aziele/pairwise-sequence-alignment
